Metadata-Version: 2.4
Name: aiagents4pharma-anshh
Version: 0.0.0
Summary: AI Agents for drug discovery, drug development, and other pharmaceutical R&D..
License-File: LICENSE
Classifier: License :: OSI Approved :: MIT License
Classifier: Operating System :: OS Independent
Classifier: Programming Language :: Python :: 3
Requires-Python: >=3.12
Requires-Dist: anndata==0.11.3
Requires-Dist: beautifulsoup4==4.13.4
Requires-Dist: cell2sentence==1.1.0
Requires-Dist: cloudscraper==1.2.71
Requires-Dist: copasi-basico==0.84
Requires-Dist: coverage==7.6.4
Requires-Dist: datasets==4.0.0
Requires-Dist: einops==0.8.0
Requires-Dist: gdown==5.2.0
Requires-Dist: gravis==0.1.0
Requires-Dist: gseapy==1.1.8
Requires-Dist: h5py==3.13.0
Requires-Dist: huggingface-hub==0.34.4
Requires-Dist: hydra-core==1.3.2
Requires-Dist: igraph==0.11.8
Requires-Dist: ipykernel==6.29.5
Requires-Dist: ipython==8.32.0
Requires-Dist: joblib==1.4.2
Requires-Dist: langchain-community==0.3.5
Requires-Dist: langchain-core==0.3.40
Requires-Dist: langchain-experimental==0.3.3
Requires-Dist: langchain-milvus==0.2.0
Requires-Dist: langchain-nvidia-ai-endpoints==0.3.9
Requires-Dist: langchain-ollama==0.2.3
Requires-Dist: langchain-openai==0.3.0
Requires-Dist: langchain==0.3.7
Requires-Dist: langgraph-supervisor==0.0.9
Requires-Dist: langgraph==0.3.34
Requires-Dist: matplotlib==3.9.2
Requires-Dist: mkdocs-include-markdown-plugin==7.1.2
Requires-Dist: mkdocs-jupyter==0.25.1
Requires-Dist: mkdocs-material==9.5.47
Requires-Dist: mkdocs==1.6.1
Requires-Dist: mkdocstrings-python==1.12.2
Requires-Dist: mkdocstrings==0.27.0
Requires-Dist: nbformat==5.10.4
Requires-Dist: numpy==1.26.4
Requires-Dist: ollama==0.4.7
Requires-Dist: openai==1.59.6
Requires-Dist: openpyxl==3.1.5
Requires-Dist: pandas==2.2.3
Requires-Dist: pcst-fast==1.0.10
Requires-Dist: plotly-express==0.4.1
Requires-Dist: plotly==5.24.1
Requires-Dist: pubchempy==1.0.4
Requires-Dist: pyarrow==21.0.0
Requires-Dist: pydantic==2.10.5
Requires-Dist: pygeneconverter==0.3
Requires-Dist: pylint==3.3.1
Requires-Dist: pymilvus==2.5.11
Requires-Dist: pypdf2==3.0.1
Requires-Dist: pypdf==6.0.0
Requires-Dist: pytest-asyncio==0.25.2
Requires-Dist: pytest==8.3.3
Requires-Dist: python-magic==0.4.27
Requires-Dist: pyzotero==1.6.9
Requires-Dist: requests==2.32.4
Requires-Dist: scanpy==1.11.0
Requires-Dist: scipy==1.15.2
Requires-Dist: seaborn==0.13.2
Requires-Dist: sentence-transformers==3.3.1
Requires-Dist: setuptools==80.9.0
Requires-Dist: streamlit-feedback==0.1.4
Requires-Dist: streamlit==1.41.1
Requires-Dist: tabulate==0.9.0
Requires-Dist: torch-geometric==2.6.1
Requires-Dist: torch==2.8.0
Requires-Dist: tqdm==4.67.1
Requires-Dist: transformers==4.55.2
Requires-Dist: umap-learn==0.5.7
Requires-Dist: xlsxwriter==3.2.5
Provides-Extra: dev
Requires-Dist: bandit==1.8.6; extra == 'dev'
Requires-Dist: mypy==1.17.1; extra == 'dev'
Requires-Dist: pip-audit==2.9.0; extra == 'dev'
Requires-Dist: pre-commit==4.3.0; extra == 'dev'
Requires-Dist: ruff==0.12.8; extra == 'dev'
Requires-Dist: safety==3.2.9; extra == 'dev'
Requires-Dist: twine==6.1.0; extra == 'dev'
